moonlightd/__init__.py
moonlightd/__main__.py
moonlightd/_version.py
moonlightd/app.py
moonlightd/common.py
moonlightd/handler/__init__.py
moonlightd/handler/_base.py
moonlightd/handler/codepages.py
moonlightd/handler/misc.py
moonlightd/handler/private.py
pytermor/__init__.py
pytermor/__main__.py
pytermor/_version.py
pytermor/ansi.py
pytermor/color.py
pytermor/common.py
pytermor/cval.py
pytermor/renderer.py
pytermor/style.py
pytermor/text.py
pytermor/utilnum.py
pytermor/utilstr.py
pytermor/utilsys.py
moonlightd-0.0.4.dist-info/LICENSE
moonlightd-0.0.4.dist-info/METADATA
moonlightd-0.0.4.dist-info/WHEEL
moonlightd-0.0.4.dist-info/entry_points.txt
moonlightd-0.0.4.dist-info/top_level.txt
moonlightd-0.0.4.dist-info/RECORD
