Metadata-Version: 2.1
Name: moonlightd
Version: 0.0.4
Summary: dl-uplink telegram bot
Home-page: https://github.com/dl-uplink/moonlightd
Author: Aleksandr Shavykin
Author-email: 0.delameter@gmail.com
Classifier: Environment :: Console
Classifier: Intended Audience :: Developers
Classifier: Programming Language :: Python :: 3
Classifier: License :: OSI Approved :: MIT License
Classifier: Operating System :: OS Independent
Requires-Python: >=3.10
License-File: LICENSE
